README
setup.cfg
setup.py
__plugin__/__init__.py
__plugin__/frontline/__init__.py
__plugin__/frontline/service.py
__plugin__/frontline_inlet/__init__.py
__plugin__/frontline_inlet/populate_default_data.py
__plugin__/livedesk/__init__.py
__plugin__/livedesk/acl.py
__plugin__/livedesk/actions.py
__plugin__/livedesk/blogs.csv
__plugin__/livedesk/gui.py
__plugin__/livedesk/populate.py
__plugin__/livedesk/populate_default_data.py
__plugin__/livedesk/posts.csv
__plugin__/livedesk/service.py
__plugin__/livedesk/upgrade.py
__plugin__/livedesk/gui-resources/__init__.py
__plugin__/livedesk/gui-resources/scripts/__init__.py
__plugin__/livedesk/gui-resources/scripts/js/__init__.py
__plugin__/livedesk/gui-resources/scripts/js/action.js
__plugin__/livedesk/gui-resources/scripts/js/add-live-blogs.js
__plugin__/livedesk/gui-resources/scripts/js/archive.js
__plugin__/livedesk/gui-resources/scripts/js/configure-blog.js
__plugin__/livedesk/gui-resources/scripts/js/dashboard.js
__plugin__/livedesk/gui-resources/scripts/js/dump-editjs.js
__plugin__/livedesk/gui-resources/scripts/js/edit-live-blogs.js
__plugin__/livedesk/gui-resources/scripts/js/manage-collaborators.js
__plugin__/livedesk/gui-resources/scripts/js/manage-feeds.js
__plugin__/livedesk/gui-resources/scripts/js/menu-live-blogs.js
__plugin__/livedesk/gui-resources/scripts/js/providers-templates.js
__plugin__/livedesk/gui-resources/scripts/js/providers.js
__plugin__/livedesk/gui-resources/scripts/js/router.js
__plugin__/livedesk/gui-resources/scripts/js/submenu-live-blogs.js
__plugin__/livedesk/gui-resources/scripts/js/models/__init__.py
__plugin__/livedesk/gui-resources/scripts/js/models/admin.js
__plugin__/livedesk/gui-resources/scripts/js/models/admins.js
__plugin__/livedesk/gui-resources/scripts/js/models/author.js
__plugin__/livedesk/gui-resources/scripts/js/models/autocollection.js
__plugin__/livedesk/gui-resources/scripts/js/models/autoposts.js
liveblog.egg-info/PKG-INFO
liveblog.egg-info/SOURCES.txt
liveblog.egg-info/dependency_links.txt
liveblog.egg-info/requires.txt
liveblog.egg-info/top_level.txt
liveblog.egg-info/zip-safe
