Metadata-Version: 1.1
Name: liveblog
Version: 1.5.0
Summary: Liveblog
Home-page: http://www.sourcefabric.org/en/superdesk/
Author: Sourcefabric
Author-email: contact@sourcefabric.org
License: GPL v3
Keywords: Liveblog
Platform: all
Classifier: Development Status :: 5 - Production/Stable
Classifier: Environment :: Web Environment
Classifier: Intended Audience :: End Users/Desktop
Classifier: License :: OSI Approved :: GNU General Public License v3 (GPLv3)
Classifier: Operating System :: OS Independent
Classifier: Programming Language :: Python :: 3.2
Classifier: Programming Language :: JavaScript
Classifier: Topic :: Internet :: WWW/HTTP :: Dynamic Content
